LICENSE
README.md
setup.py
ch9329Comm/BezierTrajectory.py
ch9329Comm/KeyboardDataComm.py
ch9329Comm/MouseDataComm.py
ch9329Comm/__init__.py
ch9329Comm.egg-info/PKG-INFO
ch9329Comm.egg-info/SOURCES.txt
ch9329Comm.egg-info/dependency_links.txt
ch9329Comm.egg-info/top_level.txt